{"pageContext":{"action":"https://codepen.io/pen/define","payload":"{\"editors\":\"0010\",\"html\":\"\",\"js\":\"class Person {\\n  constructor(firstName, lastName) {\\n    this.firstName = firstName;\\n    this.lastName = lastName;\\n  }\\n\\n  // JSON.stringify will invoke this method if it is defined\\n  toJSON() {\\n    return {\\n      fullName: `${this.firstName} ${this.lastName}`,\\n    }\\n  }\\n}\\n\\nconst yus = new Person('Yus', 'Ng');\\nconsole.log(JSON.stringify(yus)); // {\\\"fullName\\\":\\\"Yus Ng\\\"}\\n\",\"js_external\":\"\",\"js_pre_processor\":\"babel\",\"layout\":\"left\"}"}}